kgcl_schema/README.md
kgcl_schema/__init__.py
kgcl_schema/datamodel/kgcl.py
kgcl_schema/datamodel/ontology_model.py
kgcl_schema/grammar/__init__.py
kgcl_schema/grammar/kgcl.lark
kgcl_schema/grammar/kgcl_2_rdf.py
kgcl_schema/grammar/parser.py
kgcl_schema/grammar/render_operations.py
kgcl_schema/schema/__init__.py
kgcl_schema/schema/basics.yaml
kgcl_schema/schema/kgcl.yaml
kgcl_schema/schema/ontology_model.yaml
kgcl_schema/schema/prov.yaml
kgcl_schema/scripts/generate_json.py
kgcl_schema/utils.py
kgcl_schema-0.7.0.dist-info/LICENSE
kgcl_schema-0.7.0.dist-info/METADATA
kgcl_schema-0.7.0.dist-info/WHEEL
kgcl_schema-0.7.0.dist-info/entry_points.txt
kgcl_schema-0.7.0.dist-info/RECORD
