Metadata-Version: 2.1
Name: kgcl_schema
Version: 0.7.0
Summary: Schema for the KGCL project.
License: MIT
Author: Chris Mungall
Author-email: cjmungall@lbl.gov
Requires-Python: >=3.9,<4.0
Classifier: License :: OSI Approved :: MIT License
Classifier: Programming Language :: Python :: 3
Classifier: Programming Language :: Python :: 3.9
Classifier: Programming Language :: Python :: 3.10
Classifier: Programming Language :: Python :: 3.11
Classifier: Programming Language :: Python :: 3.12
Classifier: Programming Language :: Python :: 3.13
Provides-Extra: docs
Requires-Dist: curies (>=0.6.0)
Requires-Dist: lark (>=1.1.2)
Requires-Dist: linkml-runtime (>=1.1.24)
Requires-Dist: prefixmaps (>=0.2.0,<0.3.0)
